Workbook

Sheet Jahr 01_Checkliste A
A1: Jahr 01 (Checkliste A)
A2: Q1 | B2: Q2 | C2: Q3 | D2: Q4
E3: Die Kunden bezahlen. Bewegen Sie die Werteträger von Forderungen zu Kassa und Bankguthaben.
E4: Liefern Sie die fertigen Produkte gemäß Auftrag aus
E5: Notieren Sie die Herstellungskosten für den entsprechenden Auftrag in der Abrechnungstabelle auf der folgenden Seite.
E6: Stellen Sie eine Ausgangsrechnung. Platzieren Sie den Umsatzerlös bei Forderungen.
E7: Führen Sie die Endmontage in der Fertigungsstufe 2 mit den bereits vorgefertigten Fabrikaten durch. Bezahlen Sie die Montagekosten (1 M pro Los) aus Kassa und Bankguthaben
E8: Starten Sie neue Produktionsaufträge in der Fertigungsstufe 1 und bezahlen Sie die Produktionskosten (3 M pro Los) aus Kassa und Bankguthaben.
E9: Nehmen Sie die Rohmateriallieferung der Lieferanten (2 Lose) entgegen. Stellen Sie die Lieferung ins Materiallager.
E10: Bezahlen Sie das Rohmaterial (3 M pro Los) aus Kassa und Bankguthaben.
E11: Bestellen Sie Rohmaterial für das nächste Quartal. Platzieren Sie 2 leere Werteträger bei den Lieferanten.
E12: Bezahlen Sie die Gemeinkosten für Verwaltung, Vertrieb sowie Forschung und Entwicklung (6 M) aus Kassa und Bankguthaben.

Sheet Jahr 01_Abr.tab.
A1: Jahr 01 Abrechnungstabelle
A2: Auftragsnummer | B2: Liefertermin | C2: Menge (in Losen) | D2: Auftragswert | E2: Herstellungskosten | F2: Rechnung gestellt
A3: 1 | B3: 01/Q1 | C3: 2 | D3: 26 | E3: 14
A4: 2 | B4: 01/Q2 | C4: 2 | D4: 25 | E4: 14
A5: 3 | B5: 01/Q3 | C5: 2 | D5: 25 | E5: 14
A6: 4 | B6: 01/Q4 | C6: 2 | D6: 26 | E6: 14
B7: Summe

Sheet Jahr 01_Checkliste B
A1: Jahr 01 (Checkliste B) am Jahresende
A2: Aufgabe | B2: Bezahlen Sie die Zinsen für die in Anspruch genommen Kredite. Der Zinssatz beträgt 10% p.a. und ihr Kreditvolumen beläuft sich auf 100 M.
B3: Entnehmen Sie den entsprechenden Betrag aus Kassa und Bankguthaben und legen Sie diesen in den Werteträger auf dem Feld Zinsen
A4: Aufgabe | B4: Führen Sie die Abschreibung (AfA) durch. Entnehmen Sie dazu den Werteträgern auf den entsprechenden Feldern im Anlagevermögen:
B5: AfA für Gebäude (1 M)
B6: AfA für Maschinen (5 M)
B7: AfA für Betriebs- und Geschäftsausstattung (3 M)
A8: Aufgabe | B8: Legen Sie die Beträge in den Werteträger Abschreibungen in der GuV

Sheet Jahr 01_JA_GuV
A1: Jahr 01 (JA_GuV)
A2: Aufgabe | B2: Erstellen Sie eine staffelförmige GuV-Rechnung
A4: Gewinn- und Verlustrechnung (in M)
C5: Jahr 00 | D5: Jahr 01
A6: Umsatzerlöse | C6: 99 | D6: 102
A7: - Herstellungskosten | C7: -56 | D7: -56
A8: Deckungsbeitrag | C8: =SUM(C6:C7) -> 43 | D8: 46
A9: - Gemeinkosten | C9: -24 | D9: -24
A10: - Abschreibungen (AfA) | C10: -9 | D10: -9
A11: EBIT (Betriebsergebnis) | C11: =SUM(C8:C10) -> 10 | D11: 13
A12: - Zinsen | C12: -10 | D12: -10
A13: Jahresergebnis vor Steuern | C13: =SUM(C11:C12) -> 0 | D13: 3
A14: - Steuern (1/3) | C14: 0 | D14: -1
A15: Jahresergebnis nach Steuern | C15: 0 | D15: 2
C18: Buchen Sie die Steuerverbindlichkeiten
C19: Legen Sie dazu 1M (von außen !!) in einen Werteträger
C20: auf dem Feld kurzfristige Verbindlichkeiten

Sheet Jahr 01_JA_Bil
A1: Jahr 01 (JA_Bil)
A2: Aufgabe | B2: Erstellen Sie die Bilanz
A4: AKTIVA
A5: Anlagevermögen | C5: Jahr 00 | D5: Jahr 01
A6: Grundstücke | C6: 10 | D6: 10
A7: Gebäude | C7: 20 | D7: 19
A8: Maschinen | C8: 20 | D8: 15
A9: Betriebs- und Geschäfsausstattung | C9: 12 | D9: 9
A10: Summe Anlagevermögen | C10: =SUM(C6:C9) -> 62 | D10: =SUM(D6:D9) -> 53
A12: Umlaufvermögen
A13: Vorräte
A14: Roh-, Hilfs- und Betriebsstoffe | C14: 9 | D14: 9
A15: unfertige Erzeugnisse | C15: 26 | D15: 26
A16: fertige Erzeugnisse | C16: 21 | D16: 21
A17: Forderungen | C17: 25 | D17: 26
A18: Kassa und Bankguthaben | C18: 24 | D18: 35
A19: Summe Umlaufvermögen | C19: =SUM(C14:C18) -> 105 | D19: =SUM(D14:D18) -> 117
A20: SUMME AKTIVA | C20: =C10+C19 -> 167 | D20: 170
A22: PASSIVA
A23: Eigenkapital
A24: Grundkapital | C24: 60 | D24: 60
A25: Gewinnrücklage | C25: 7 | D25: 7
A26: Gewinn/(Verlust lfd. Jahr n. Steuern | C26: 0 | D26: 2
A27: Summe Eigenkapital | C27: =SUM(C24:C26) -> 67 | D27: 69
A29: Fremdkapital
A30: Langfristiges Fremdkapital | C30: 100 | D30: 100
A31: Kurzfristiges Fremdkapital | C31: 0 | D31: 1
A32: Summe Fremdkapital | C32: =SUM(C30:C31) -> 100 | D32: 101
A33: SUMME PASSIVA | C33: =C27+C32 -> 167 | D33: 170

Sheet Jahr 01_JA_KPIs
A1: Jahr 01 (JA_KPIs)
A2: Aufgabe: | B2: Übertragen Sie die Ergebnisse aus der GuV und der Bilanz in das Erfolgskennzahlen-System, die sogenannte DuPont-Matrix,
B3: Berechnen Sie die Rentabilität genauer die Gesamtkapitalrentabilität (ROI) und die Eigenkapitalrentabilität (ROE)
B4: Ermitteln Sie außerdem die Umsatzrentabilität (ROS)
G6: Umsatzrentabilität (ROS)
A7: Umsatzerlöse | G7: Jahr 00 | H7: Jahr 01
A8: Jahr 00 | B8: Jahr 01 | G8: =G13/A9 -> 0.1010101 | H8: =E11/B9*100 -> 45.098039
A9: ='Jahr 01_JA_GuV'!$C$6 -> 99 | B9: 102 | D9: Deckungsbeitrag
D10: Jahr 00 | E10: Jahr 01
A11: Herstellungskosten | D11: =A9+A13 -> 43 | E11: 46 | G11: EBIT | J11: Zinsen + Steuern
A12: Jahr 00 | B12: Jahr 01 | G12: Jahr 00 | H12: Jahr 01 | J12: Jahr 00 | K12: Jahr 01
A13: ='Jahr 01_JA_GuV'!$C$7 -> -56 | B13: -56 | D13: Gemeinkosten + Abschreibungen | G13: ='Jahr 01_JA_GuV'!$C$11 -> 10 | J13: ='Jahr 01_JA_GuV'!$C$14+'Jahr 01_JA_GuV'!$C$12 -> -10
D14: Jahr 00 | E14: Jahr 01
D15: ='Jahr 01_JA_GuV'!$C$9+'Jahr 01_JA_GuV'!$C$10 -> -33 | E15: -33 | J15: Gewinn/Verlust nach Steuern
J16: Jahr 00 | K16: Jahr 01
J17: =G13+J13 -> 0
A18: Anlagevermögen | G18: Gesamtkapitalrentabilität (ROI)
A19: Jahr 00 | B19: Jahr 01 | G19: Jahr 00 | H19: Jahr 01 | J19: Eigenkapitalrentabilität (ROE)
A20: ='Jahr 01_JA_Bil'!C10 -> 62 | B20: 53 | G20: =G13/D26 -> 0.05988024 | J20: Jahr 00 | K20: Jahr 01
J21: ='Jahr 01_JA_Bil'!C22 -> 0
A22: Vorräte
A23: Jahr 00 | B23: Jahr 01
A24: ='Jahr 01_JA_Bil'!C14+'Jahr 01_JA_Bil'!C15+'Jahr 01_JA_Bil'!C16 -> 56 | B24: 56 | D24: Gesamtvermögen bzw. -kap. | J24: Eigenkapital
D25: Jahr 00 | E25: Jahr 01 | J25: Jahr 00 | K25: Jahr 01
A26: Forderungen | D26: =A20+A24+A28+A32 -> 167 | E26: 170 | J26: ='Jahr 01_JA_Bil'!C27 -> 67
A27: Jahr 00 | B27: Jahr 01
A28: ='Jahr 01_JA_Bil'!C17 -> 25 | B28: 26 | J28: Fremdkapital
J29: Jahr 00 | K29: Jahr 01
A30: Kassa und Bankguth. | J30: ='Jahr 01_JA_Bil'!C32 -> 100
A31: Jahr 00 | B31: Jahr 01
A32: ='Jahr 01_JA_Bil'!C18 -> 24 | B32: 35
E33: Umsatzrendite = (EBIT * 100)/Umsatzerlöse
E34: Gesamtkapitalrendite = (EBIT * 100) / Gesamtkapital
E35: Eigenkapitalrendite = (Gewinn/Verlust nach Steuern / Eigenkapital

Sheet Jahr 01_CashFlow
A1: Jahr 01 (JA_CashFlow-Statement)
A3: Aufgabe | B3: Übertragen Sie die Ergebnisse aus der Gewinn- und Verlustrechnung
B4: und der Bilanz in die Kapitalflussrechnung (Cash Flow-Statement)
D5: Jahr 01
A6: 1 | C6: Gewinn nach Steuern
A7: 2 | C7: Abschreibung (AfA)
A8: 3 | C8: Zunahme der Vorräte
C9: Abnahme der Vorräte
A10: 4 | C10: Zunahme der Forderungen
C11: Abnahme der Forderungen
A12: 5 | C12: Zunahme der Verbindlichkeiten aus L. & L.
C13: Abnahme der Verbindlichkeiten
A14: 6 | C14: Cash Flow aus der Geschäftstätigkeit (1-5)
A15: 7 | C15: Investitionen
A16: 8 | C16: Erlöse aus Anlagenabgängen
A17: 9 | C17: Cash Flow aus der Investitionstätigkeit (7-8)
A18: 10 | C18: Zunahme der Verbindlichkeiten
C19: Abnahme der Verbindlichkeiten
A20: 12 | C20: Einzahlungen aus der Ausgabe von Aktien
A21: 13 | C21: Bezahlte Dividenden
A22: 14 | C22: Cash Flow aus der Finanzierungstätigkeit (10-13)
A23: 15 | C23: Veränderungen der Zahlungsmittel (6+9+14)
B26: * L. & L. heißt Lieferungen und Leistungen (auf Ziel)
B27: ** ohne Verbindlichkeiten aus Lieferungen und Leistungen
